{"employees":[{"HI_dateOfIssue":"","HI_registryNumber":"","HI_serialNumber":"","ID_dateOfIssue":"","ID_muncipalityOfIssue":"","ID_registryNumber":"","ID_serialNumber":"","accountPayout1":"","accountPayout2":"","address":"","allowanceInsurance":"","allowanceMeal":"","amount":"","average1":"","average2":"","average3":"","coefficient1":"","coefficient2":"","comment":"","dateOfBirth":"","email":"","employmentBooklet_DateOfIssue":"0002-02-02","employmentBooklet_EmploymentCode":"2","employmentBooklet_Muncipality":"2","employmentBooklet_RegistryNumber":"2","employmentBooklet_SerialNumber":"2","employmentPosition":"2","employmentSection":"2","employmentUnit":"2","externalYoS_periods":[{"from":697075200000,"till":697161600000}],"externalYoS_total":86400000,"familyMembers":"","firstName":"Nikola","group":"2","hours":"","id":"00002","internalYoS_periods":[{"from":791769600000,"till":794188800000},{"from":828230400000,"till":831859200000}],"internalYoS_total":6048000000,"jmbg":"2405995730054","lastName":"Tasic","middleName":"Slavisa","muncipality":"","muncipalityEmployment":"","muncipalityPayout1":"","muncipalityPayout2":"","muncipalityResidency":"","numberOfKids":"","percentage":"","points":"2","rating":"2","realQualification":"2","reducedYoS":"","sex":"","totalYoS":6048000000,"transportAllowanceCategory1":"","transportAllowanceCategory2":"","transportAllowanceCategory3":"","typeEmployee":"2","typeEmployment":"2","typeReceiver":"2","verifiedQualification":"2","zip":""},{"HI_dateOfIssue":"","HI_muncipalityOfIssue":"","HI_registryNumber":"","HI_serialNumber":"","ID_dateOfIssue":"","ID_muncipalityOfIssue":"","ID_registryNumber":"","ID_serialNumber":"","accountPayout1":"","accountPayout2":"","address":"","allowanceInsurance":"","allowanceMeal":"","amount":"","average1":"","average2":"","average3":"","coefficient1":"","coefficient2":"","comment":"","dateOfBirth":"","email":"","employmentBooklet_DateOfIssue":"","employmentBooklet_EmploymentCode":"","employmentBooklet_Muncipality":"","employmentBooklet_RegistryNumber":"","employmentBooklet_SerialNumber":"","employmentPosition":"","employmentSection":"","employmentUnit":"","externalYoS_periods":[],"externalYoS_total":0,"familyMembers":"","firstName":"Aleksa","group":"","hours":"","id":"00003","internalYoS_periods":[],"internalYoS_total":0,"jmbg":"2404995730054","lastName":"Stojanovic","middleName":"Dragan","muncipality":"","muncipalityEmployment":"","muncipalityPayout1":"","muncipalityPayout2":"","muncipalityResidency":"","numberOfKids":"","percentage":"","points":"","rating":"","realQualification":"","reducedYoS":"","sex":"","totalYoS":0,"transportAllowanceCategory1":"","transportAllowanceCategory2":"","transportAllowanceCategory3":"","typeEmployee":"","typeEmployment":"","typeReceiver":"","verifiedQualification":"","zip":""},{"HI_dateOfIssue":"","HI_muncipalityOfIssue":"","HI_registryNumber":"","HI_serialNumber":"","ID_dateOfIssue":"","ID_muncipalityOfIssue":"","ID_registryNumber":"","ID_serialNumber":"","accountPayout1":"","accountPayout2":"","address":"","allowanceInsurance":"","allowanceMeal":"","amount":"","average1":"","average2":"","average3":"","coefficient1":"","coefficient2":"","comment":"","dateOfBirth":"","email":"","employmentBooklet_DateOfIssue":"","employmentBooklet_EmploymentCode":"14","employmentBooklet_Muncipality":"","employmentBooklet_RegistryNumber":"15155255111","employmentBooklet_SerialNumber":"41254155125","employmentPosition":"11","employmentSection":"23","employmentUnit":"34","externalYoS_periods":[],"externalYoS_total":0,"familyMembers":"","firstName":"Doe ","group":"Q","hours":"","id":"00004","internalYoS_periods":[],"internalYoS_total":0,"jmbg":"2403995730054","lastName":"John","middleName":"Virgil","muncipality":"","muncipalityEmployment":"","muncipalityPayout1":"","muncipalityPayout2":"","muncipalityResidency":"","numberOfKids":"","percentage":"","points":"24","rating":"3","realQualification":"12","reducedYoS":"","sex":"","totalYoS":0,"transportAllowanceCategory1":"","transportAllowanceCategory2":"","transportAllowanceCategory3":"","typeEmployee":"19","typeEmployment":"3","typeReceiver":"2","verifiedQualification":"12","zip":""},{"HI_dateOfIssue":"","HI_muncipalityOfIssue":"","HI_registryNumber":"","HI_serialNumber":"","ID_dateOfIssue":"","ID_muncipalityOfIssue":"","ID_registryNumber":"","ID_serialNumber":"","accountPayout1":"","accountPayout2":"","address":"","allowanceInsurance":"","allowanceMeal":"","amount":"","average1":"","average2":"","average3":"","coefficient1":"","coefficient2":"","comment":"","dateOfBirth":"","email":"","employmentBooklet_DateOfIssue":"","employmentBooklet_EmploymentCode":"","employmentBooklet_Muncipality":"","employmentBooklet_RegistryNumber":"151252151","employmentBooklet_SerialNumber":"121515125","employmentPosition":"","employmentSection":"","employmentUnit":"","externalYoS_periods":[],"externalYoS_total":0,"familyMembers":"","firstName":"Test","group":"","hours":"","id":"00006","internalYoS_periods":[{"from":949449600000,"till":983577600000}],"internalYoS_total":34128000000,"jmbg":"2404995730053","lastName":"Test","middleName":"Test","muncipality":"","muncipalityEmployment":"","muncipalityPayout1":"","muncipalityPayout2":"","muncipalityResidency":"","numberOfKids":"","percentage":"","points":"","rating":"","realQualification":"","reducedYoS":"","sex":"","totalYoS":34128000000,"transportAllowanceCategory1":"","transportAllowanceCategory2":"","transportAllowanceCategory3":"","typeEmployee":"","typeEmployment":"","typeReceiver":"","verifiedQualification":"","zip":""}]}